scix/__init__.py
scix/main.py
scix-0.0.1.dist-info/LICENSE
scix-0.0.1.dist-info/METADATA
scix-0.0.1.dist-info/WHEEL
scix-0.0.1.dist-info/top_level.txt
scix-0.0.1.dist-info/RECORD
