Metadata-Version: 2.1
Name: scix
Version: 0.0.1
Summary: Scientific computing to the next level.
Author-email: Zoey Hu <zoey.zyhu@gmail.com>
Classifier: Programming Language :: Python :: 3
Classifier: License :: OSI Approved :: MIT License
Classifier: Operating System :: OS Independent
Requires-Python: >=3.7
License-File: LICENSE
